salute/__init__.py
salute/app/__init__.py
salute/app/app.py
salute/app/config.py
salute/cli/__init__.py
salute/cli/cli.py
salute/cli/salute_init.py
salute/cli/system.py
salute/cli/actions/__init__.py
salute/cli/actions/init_scenario.py
salute/common/__init__.py
salute/common/assets/__init__.py
salute/common/assets/items.py
salute/common/models/__init__.py
salute/common/models/request_message.py
salute/common/models/response_message.py
salute/common/models/message/__init__.py
salute/common/models/message/app_info.py
salute/common/models/message/device.py
salute/common/models/message/entities.py
salute/common/models/message/message.py
salute/common/models/message/name.py
salute/common/models/message/payload.py
salute/common/models/message/request_payload.py
salute/common/models/message/response_payload.py
salute/common/models/message/text.py
salute/common/models/message/user.py
salute/common/models/scenario/__init__.py
salute/common/models/scenario/scenario.py
salute/common/models/scenario/scenario_app.py
salute/common/models/scenario/utils.py
salute/common/scenario_connector/__init__.py
salute/common/scenario_connector/connect.py
salute/common/store/__init__.py
salute/common/store/store.py
salute/common/utils/__init__.py
salute/common/utils/load_data.py
salute/plugins/__init__.py
salute/plugins/use.py
salute/utils/__init__.py
salute/utils/const.py
salute-0.7.15.dist-info/METADATA
salute-0.7.15.dist-info/WHEEL
salute-0.7.15.dist-info/entry_points.txt
salute-0.7.15.dist-info/top_level.txt
salute-0.7.15.dist-info/RECORD
