Metadata-Version: 2.4
Name: salute
Version: 0.7.15
Summary: Add your description here
Requires-Python: <4.0,>=3.13
Requires-Dist: loguru>=0.7.3
Requires-Dist: pydantic>=2.11.3
Requires-Dist: sanic>=25.3.0
Requires-Dist: twine>=6.1.0
Requires-Dist: python-decouple<4.0,>=3.8
Requires-Dist: build>=1.2.2.post1
